sqlalchemy_firebird/__init__.py
sqlalchemy_firebird/base.py
sqlalchemy_firebird/fb_info25.py
sqlalchemy_firebird/fb_info30.py
sqlalchemy_firebird/fb_info40.py
sqlalchemy_firebird/fdb.py
sqlalchemy_firebird/firebird.py
sqlalchemy_firebird/infrastructure.py
sqlalchemy_firebird/provision.py
sqlalchemy_firebird/requirements.py
sqlalchemy_firebird/types.py
sqlalchemy_firebird-2.1.dist-info/AUTHORS
sqlalchemy_firebird-2.1.dist-info/LICENSE
sqlalchemy_firebird-2.1.dist-info/METADATA
sqlalchemy_firebird-2.1.dist-info/WHEEL
sqlalchemy_firebird-2.1.dist-info/entry_points.txt
sqlalchemy_firebird-2.1.dist-info/top_level.txt
sqlalchemy_firebird-2.1.dist-info/RECORD
