Metadata-Version: 2.1
Name: sqlalchemy-firebird
Version: 2.1
Summary: Firebird for SQLAlchemy
Author: F.D.Castel
Author-email: Paul Graves-DesLauriers <paul@dexmicro.com>
Maintainer-email: Paul Graves-DesLauriers <paul@dexmicro.com>
License: Copyright 2005-2023 SQLAlchemy authors and contributors <see AUTHORS file>.
Project-URL: Documentation, https://github.com/pauldex/sqlalchemy-firebird/wiki
Project-URL: Source, https://github.com/pauldex/sqlalchemy-firebird
Project-URL: Tracker, https://github.com/pauldex/sqlalchemy-firebird/issues
Keywords: SQLAlchemy,Firebird,fdb,firebird-driver
Classifier: Development Status :: 4 - Beta
Classifier: Intended Audience :: Developers
Classifier: License :: OSI Approved :: MIT License
Classifier: Programming Language :: Python
Classifier: Programming Language :: Python :: 3
Classifier: Programming Language :: Python :: Implementation :: CPython
Classifier: Topic :: Database :: Front-Ends
Classifier: Operating System :: OS Independent
Requires-Python: !=3.0.*,!=3.1.*,!=3.2.*,!=3.3.*,!=3.4.*,!=3.5.*,>=2.7
License-File: LICENSE
License-File: AUTHORS
Requires-Dist: packaging
Requires-Dist: SQLAlchemy <2.0,>=1.4 ; python_version < "3.8"
Requires-Dist: fdb ; python_version < "3.8"
Requires-Dist: SQLAlchemy >=2.0 ; python_version >= "3.8"
Requires-Dist: firebird-driver ; python_version >= "3.8"
Provides-Extra: dev
Requires-Dist: pytest ; extra == 'dev'
Requires-Dist: black ; extra == 'dev'
Requires-Dist: flake8 ; extra == 'dev'
Requires-Dist: build ; extra == 'dev'
Requires-Dist: twine ; extra == 'dev'
Provides-Extra: test
Requires-Dist: pytest ; extra == 'test'
